package org.ajester;

import java.util.HashMap;
import java.util.Map;

public class ConstantLookup {
	Map map = new HashMap();
	
	public ConstantLookup() {
		map.put(new Integer(0), "NOP");
		map.put(new Integer(1), "ACONST_NULL");
		map.put(new Integer(2), "ICONST_M1");
		map.put(new Integer(3), "ICONST_0 (false)");
		map.put(new Integer(4), "ICONST_1 (true)");
		map.put(new Integer(5), "ICONST_2");
		map.put(new Integer(6), "ICONST_3");
		map.put(new Integer(7), "ICONST_4");
		map.put(new Integer(8), "ICONST_5");
		map.put(new Integer(9), "LCONST_0");
		map.put(new Integer(10), "LCONST_1");
		map.put(new Integer(11), "FCONST_0");
		map.put(new Integer(12), "FCONST_1");
		map.put(new Integer(13), "FCONST_2");
		map.put(new Integer(14), "DCONST_0");
		map.put(new Integer(15), "DCONST_1");
		map.put(new Integer(16), "BIPUSH");
		map.put(new Integer(17), "SIPUSH");
		map.put(new Integer(18), "LDC");
		map.put(new Integer(21), "ILOAD");
		map.put(new Integer(22), "LLOAD");
		map.put(new Integer(23), "FLOAD");
		map.put(new Integer(24), "DLOAD");
		map.put(new Integer(25), "ALOAD");
		map.put(new Integer(46), "IALOAD");
		map.put(new Integer(47), "LALOAD");
		map.put(new Integer(48), "FALOAD");
		map.put(new Integer(49), "DALOAD");
		map.put(new Integer(50), "AALOAD");
		map.put(new Integer(51), "BALOAD");
		map.put(new Integer(52), "CALOAD");
		map.put(new Integer(53), "SALOAD");
		map.put(new Integer(54), "ISTORE");
		map.put(new Integer(55), "LSTORE");
		map.put(new Integer(56), "FSTORE");
		map.put(new Integer(57), "DSTORE");
		map.put(new Integer(58), "ASTORE");
		map.put(new Integer(79), "IASTORE");
		map.put(new Integer(80), "LASTORE");
		map.put(new Integer(81), "FASTORE");
		map.put(new Integer(82), "DASTORE");
		map.put(new Integer(83), "AASTORE");
		map.put(new Integer(84), "BASTORE");
		map.put(new Integer(85), "CASTORE");
		map.put(new Integer(86), "SASTORE");
		map.put(new Integer(87), "POP");
		map.put(new Integer(88), "POP2");
		map.put(new Integer(89), "DUP");
		map.put(new Integer(90), "DUP_X1");
		map.put(new Integer(91), "DUP_X2");
		map.put(new Integer(92), "DUP2");
		map.put(new Integer(93), "DUP2_X1");
		map.put(new Integer(94), "DUP2_X2");
		map.put(new Integer(95), "SWAP");
		map.put(new Integer(96), "IADD");
		map.put(new Integer(97), "LADD");
		map.put(new Integer(98), "FADD");
		map.put(new Integer(99), "DADD");
		map.put(new Integer(100), "ISUB");
		map.put(new Integer(101), "LSUB");
		map.put(new Integer(102), "FSUB");
		map.put(new Integer(103), "DSUB");
		map.put(new Integer(104), "IMUL");
		map.put(new Integer(105), "LMUL");
		map.put(new Integer(106), "FMUL");
		map.put(new Integer(107), "DMUL");
		map.put(new Integer(108), "IDIV");
		map.put(new Integer(109), "LDIV");
		map.put(new Integer(110), "FDIV");
		map.put(new Integer(111), "DDIV");
		map.put(new Integer(112), "IREM");
		map.put(new Integer(113), "LREM");
		map.put(new Integer(114), "FREM");
		map.put(new Integer(115), "DREM");
		map.put(new Integer(116), "INEG");
		map.put(new Integer(117), "LNEG");
		map.put(new Integer(118), "FNEG");
		map.put(new Integer(119), "DNEG");
		map.put(new Integer(120), "ISHL");
		map.put(new Integer(121), "LSHL");
		map.put(new Integer(122), "ISHR");
		map.put(new Integer(123), "LSHR");
		map.put(new Integer(124), "IUSHR");
		map.put(new Integer(125), "LUSHR");
		map.put(new Integer(126), "IAND");
		map.put(new Integer(127), "LAND");
		map.put(new Integer(128), "IOR");
		map.put(new Integer(129), "LOR");
		map.put(new Integer(130), "IXOR");
		map.put(new Integer(131), "LXOR");
		map.put(new Integer(132), "IINC");
		map.put(new Integer(133), "I2L");
		map.put(new Integer(134), "I2F");
		map.put(new Integer(135), "I2D");
		map.put(new Integer(136), "L2I");
		map.put(new Integer(137), "L2F");
		map.put(new Integer(138), "L2D");
		map.put(new Integer(139), "F2I");
		map.put(new Integer(140), "F2L");
		map.put(new Integer(141), "F2D");
		map.put(new Integer(142), "D2I");
		map.put(new Integer(143), "D2L");
		map.put(new Integer(144), "D2F");
		map.put(new Integer(145), "I2B");
		map.put(new Integer(146), "I2C");
		map.put(new Integer(147), "I2S");
		map.put(new Integer(148), "LCMP");
		map.put(new Integer(149), "FCMPL");
		map.put(new Integer(150), "FCMPG");
		map.put(new Integer(151), "DCMPL");
		map.put(new Integer(152), "DCMPG");
		map.put(new Integer(153), "IFEQ");
		map.put(new Integer(154), "IFNE");
		map.put(new Integer(155), "IFLT");
		map.put(new Integer(156), "IFGE");
		map.put(new Integer(157), "IFGT");
		map.put(new Integer(158), "IFLE");
		map.put(new Integer(159), "IF_ICMPEQ");
		map.put(new Integer(160), "IF_ICMPNE");
		map.put(new Integer(161), "IF_ICMPLT");
		map.put(new Integer(162), "IF_ICMPGE");
		map.put(new Integer(163), "IF_ICMPGT");
		map.put(new Integer(164), "IF_ICMPLE");
		map.put(new Integer(165), "IF_ACMPEQ");
		map.put(new Integer(166), "IF_ACMPNE");
		map.put(new Integer(167), "GOTO");
		map.put(new Integer(168), "JSR");
		map.put(new Integer(169), "RET");
		map.put(new Integer(170), "TABLESWITCH");
		map.put(new Integer(171), "LOOKUPSWITCH");
		map.put(new Integer(172), "IRETURN");
		map.put(new Integer(173), "LRETURN");
		map.put(new Integer(174), "FRETURN");
		map.put(new Integer(175), "DRETURN");
		map.put(new Integer(176), "ARETURN");
		map.put(new Integer(177), "RETURN");
		map.put(new Integer(178), "GETSTATIC");
		map.put(new Integer(179), "PUTSTATIC");
		map.put(new Integer(180), "GETFIELD");
		map.put(new Integer(181), "PUTFIELD");
		map.put(new Integer(182), "INVOKEVIRTUAL");
		map.put(new Integer(183), "INVOKESPECIAL");
		map.put(new Integer(184), "INVOKESTATIC");
		map.put(new Integer(185), "INVOKEINTERFACE");
		map.put(new Integer(187), "NEW");
		map.put(new Integer(188), "NEWARRAY");
		map.put(new Integer(189), "ANEWARRAY");
		map.put(new Integer(190), "ARRAYLENGTH");
		map.put(new Integer(191), "ATHROW");
		map.put(new Integer(192), "CHECKCAST");
		map.put(new Integer(193), "INSTANCEOF");
		map.put(new Integer(194), "MONITORENTER");
		map.put(new Integer(195), "MONITOREXIT");
		map.put(new Integer(197), "MULTIANEWARRAY");
		map.put(new Integer(198), "IFNULL");
		map.put(new Integer(199), "IFNONNULL");
	}
	
	public String getName(int opcode) {
		return (String) map.get(new Integer(opcode));
	}
}
